{
  "id": "song_00316",
  "title": "Xin Lỗi",
  "artist": "Hồ Tiến Đạt",
  "genre": "Điệu Ballad",
  "lyrics": "Xin lỗi cơn mơ vừa qua, Xin lỗi cơn đau vừa xa lạ. Xin lỗi nỗi vui còn vương lại, Nụ cười đôi khi đắng cay lòng này. Xin lỗi những đêm mùa đông, Thân ấm ấp trên bàn tay hiền lành, Xin lỗi quán quen phải cùng tôi, tập quên một người. Có tình yêu vượt qua mùa đông, Gục chết sau đêm mùa xuân. Có người mang bình yên về nơi nào, Xa xôi chẳng bến bờ. Có người gieo vào nhau niềm tin, Tính ấm nóng không thể rời xa, Có người đi thật xa, thật xa chẳng trở về... Xin lỗi cơn mơ vừa qua, Xin lỗi cơn đau vừa xa lạ. Xin lỗi nỗi vui còn vương lại, Nụ cười đôi khi đắng cay lòng này. (Lời hát viết ra vì tôi, Vì biết nói ra lệ rơi, Xin lỗi đáng ra phải vui, thế mà…﻿) x2"
}