{
  "id": "song_00624",
  "title": "Tong Hua",
  "artist": "Michael Wong / Quang Lương",
  "genre": "Điệu Ballad",
  "lyrics": ".   Wang Le You Dou Jiu Zai Mei Ting Dao Ni Dui Wo Shuo Ni Zui Ai De Gu Shi Wo Xiang Le Hen Jiu Wo Kai Shi Huang Le Shi Bu Shi Wo You Zuo Cuo Shen Me Ni Ku Zhe Dui Wo Shuo Tong Hua Li Dou Shi Pian Ren De Wo Bu Ke Neng Shi Ni De Wang Zi Ye Xu Ni Bu Hui Dong Cong Ni Shuo Ai Wo Yi Hou Wo De Tian Kong Xin Xin Dou Liang Le Wo Yuan Bian Cheng Tong Hua Li Ni Ai De Na Ge Tian Shi Zhang Kai Shuang Shou Bian Cheng Chi Bang Shou Hu Ni Ni Yao Xiang Xin Xiang Xin Wo Men Hui Xiang Tong Hua Gu Shi Li Xing Fu He Kuai Le Shi Jie Ju Ni Ku Zhe Dui Wo Shuo Tong Hua Li Dou Shi Pian Ren De Wo Bu Ke Neng Shi Ni De Wang Zi Ye Xu Ni Bu Hui Dong Cong Ni Shuo Ai Wo Yi Hou Wo De Tian Kong Xin Xin Dou Liang Le Wo Yuan Bian Cheng Tong Hua Li Ni Ai De Na Ge Tian Shi Zhang Kai Shuang Shou Bian Cheng Chi Bang Shou Hu Ni Ni Yao Xiang Xin Xiang Xin Wo Men Hui Xiang Tong Hua Gu Shi Li Xing Fu He Kuai Le Shi Jie Ju Wo Yuan Bian Cheng Tong Hua Li Ni Ai De Na Ge Tian Shi Zhang Kai Shuang Shou Bian Cheng Chi Bang Shou Hu Ni Ni Yao Xiang Xin Xiang Xin Wo Men Hui Xiang Tong Hua Gu Shi Li Xing Fu He Kuai Le Shi Jie Ju Wo Yuan Bian Cheng Tong Hua Li Ni Ai De Na Ge Tian Shi Zhang Kai Shuang Shou Bian Cheng Chi Bang Shou Hu Ni Ni Yao Xiang Xin Xiang Xin Wo Men Hui Xiang Tong Hua Gu Shi Li Xing Fu He Kuai Le Shi Jie Ju Yi qi xie wo men de jie ju"
}