{
  "id": "song_01231",
  "title": "Ngu Nghếch",
  "artist": "Hoàng Dũng",
  "genre": "Điệu Ballad",
  "lyrics": "tone Kể từ lần cuối hai ta nói câu “thôi đành”, Liệu rằng cuộc sống có giúp em quên đi thật nhanh Liệu rằng những vết nứt trong tim em Còn trực chờ đau hơn mỗi khi rung động Chặng đường mà đôi ta đi bên nhau không dài Trải đầy là những tiếc nuối anh mang theo ngày mai Anh thì ôm chất chứa mà chẳng ai hiểu thấu (huh huh..) Có ai hạnh phúc chỉ với những câu tình ca ? (huh huh..) Và dù anh có hát hàng trăm câu hát ngọt ngào thì, Đáng buồn thay, Anh vẫn cứ luôn là kẻ ngốc Chuyện của ta vỡ tan như chưa từng trông mong Là những lần em khóc giữa mênh mông người Còn anh buông ngày ngu nghếch cho đêm cuốn trôi Anh cứ đi nhưng chẳng tới Chẳng thể tới với những yêu thương dù nhỏ nhoi Trượt dài với những nỗi cô đơn chẳng thể nói Để em xa vời lại ngồi tiếc nuối Vì ngỡ yêu như trọn đời Những ngây ngô mang con tim anh vụn nát Cũng như anh chẳng làm được như những điều anh từng hát Vẫn luôn cố chấp vô tình dẫu đôi ba lần khác Vẫn chọn cách rời xa dẫu cho điều này thật ác.. Chợt tỉnh giấc khờ dại chỉ còn lại chơi vơi Người đau nhất, đúng ra chẳng phải là hai chúng ta (huh huh..) Có ai hạnh phúc chỉ với những câu tình ca ? (huh huh..) Và dù anh có hát hàng trăm câu hát ngọt ngào thì, Đáng buồn thay, Anh vẫn cứ luôn là kẻ ngốc Chuyện của ta vỡ tan như chưa từng trông mong Là những lần em khóc giữa mênh mông người Còn anh buông ngày ngu nghếch cho đêm cuốn trôi Anh cứ đi nhưng chẳng tới Chẳng thể tới với những yêu thương dù nhỏ nhoi Trượt dài với những nỗi cô đơn chẳng thể nói Để em xa vời lại ngồi tiếc nuối Vì ngỡ yêu như trọn đời Một người ngậm ngùi đổi thay Tìm người đường về chẳng thấy."
}