{
  "id": "song_01428",
  "title": "Vững An (Still).",
  "artist": "Nhạc Tin Lành",
  "genre": "Điệu Ballad",
  "lyrics": "1.X in d ấu  c on nơi c ánh  t ay   C ha, c he phủ c on nhờ b óng thiêng Cha quyền nă ng. 2.C on  ư ớc  ng uyện nương n áu   G iê - xu . Qu yền năng N gài làm v ững tin con cậy t rông. ĐK: D ù giông tố khiếp k inh sóng g ió vây  q uanh, n guyện xin Chúa dắt đ ưa vượt q ua bão t ố. L ạy Cha thánh hiển v inh Vua t rên dương g ian, c on luôn vững l òng vì biết C ha bên c on."
}