{
  "id": "song_01470",
  "title": "Chết Đi Cho Rồi",
  "artist": "CAM",
  "genre": "Điệu Ballad",
  "lyrics": "Hợp âm viết ở Tone - Tone gốc Gm: Capo 5 Giờ thì ta chết đi cho rồi , trên cao bầu trời kia như sập tối Nơi ta được nghỉ ngơi, vui đùa thảnh thơi, ta thôi rã rời Giờ thì em sống sao cho vừa , cho anh lại được ôm em lần nữa Ấp bờ môi này, xếp bờ vai gầy, nơi em dang tay Giờ thì ta chết đi cho rồi , trên cao bầu trời kia như sập tối Nơi ta được nghỉ ngơi, vui đùa thảnh thơi, ta thôi rã rời Giờ thì em sống sao cho vừa , cho anh lại được ôm em lần nữa Ấp bờ môi này, xếp bờ vai gầy, nơi em dang tay Giờ thì ta chết đi cho rồi , trên cao bầu trời kia như sập tối Nơi ta được nghỉ ngơi, vui đùa thảnh thơi, ta thôi rã rời Giờ thì em sống sao cho vừa , cho anh lại được ôm em lần nữa Ấp bờ môi này, xếp bờ vai gầy, nơi em dang tay"
}