{
  "id": "song_01669",
  "title": "Gã Giang Hồ",
  "artist": "Lã Phong Lâm",
  "genre": "Điệu Ballad",
  "lyrics": "Tone Lại một ngày nữa sắp trôi qua rồi ngồi nơi đây nhìn mặt trời xuống núi ăn năn xám hối để đời thứ tha bao nhiêu tội lỗi của ngày hôm qua như vết dao cắt ngang lòng ta. Mặt trời đã khuất phía xa chân trời màn đêm rơi rơi vào bóng tối có nấm mộ tàn của thằng bạn tôi nó đã lìa đời khi vừa đôi mươi ôi xót thương thay một kiếp tù đầy. Đã có những lúc ta ngồi nghĩ bao năm dọc ngang để đc gì e yêu cũng đã bỏ ta đi đường về mịt mù ko lối ôi thân ta mang bao tội lỗi lao như con thiêu thân vì anh em phát súng cuối cùng vang trong đêm rồi gục đầu một mình ta nhận hết. Ôi những năm tháng nơi trại giam thân xác ta giờ đây hoang tàn nơi phương xa người yêu dấu ơi gửi đến e một lời xin lỗi đã bao đêm ta trong bóng tối nghĩ đến e mà ta nhói lòng ta đang đau người có biết ko ai thương ta một gã giang hồ."
}