{
  "id": "song_01710",
  "title": "I Need You",
  "artist": "BTS",
  "genre": "Điệu Ballad",
  "lyrics": "Tone Fall (everything) Fall (everything) Fall (everything) Fall (everything) Fall (everything) Fall (everything) neo ttaeme na ireohke mangajyeo geumanhallae ije neo an gajyeo mot hagesseo mwot gataseo jebal pinggye gateun geon samgajwo niga nahante ireom an dwae niga han modeun mareun andae jinsireul garigo nal jjijeo nal jjigeo na michyeo da sirheo But you’re my everything (You’re my) Everything (You’re my) Everything (You’re my) mianhae (I hate u) saranghae (I hate u) yongseohae I need you girl wae honja saranghago honjaseoman ibyeolhae I need you girl wae dachil geol almyeonseo jakku niga piryohae I need you girl neon areum dawo I need you girl neomu chagawo I need you girl (I need you girl) I need you girl I need you girl It goes round & round na wae ja kku doraoji I go down & down ijjeum doemyeon naega baboji na mu seun jiseul haebwado eo jjeol sugaeobtdago bunmyeong nae simjang, nae maeum, nae gaseuminde tto honjat malhane (tto honjat malhane) tto honjat malhane (tto honjatmalhane) neon amu mal an hae a jebal naega jalhalge haneureun tto parahge (haneureun tto parahge) haneuri paraeseo haessari bitnaseo nae nunmu ri deo jal boina bwa wae naneun neoinji wae hapil neoinji wae neoreul tteonal suga eobtneunji I need you girl wae honja saranghago honjaseoman ibyeolhae I need you girl wae dachil geol almyeonseo jakku niga piryohae I need you girl neon areum dawo I need you girl neomu chagawo I need you girl (I need you girl) I need you girl I need you girl Girl charari charari heeo jijago haejwo Girl sarangi sarangi ani eotdago haejwo naegen geureol yonggigaeobseo naege majimak seonmureul jwo deoneun doragal su eobtdo rok wae honja saranghago honjaseoman ibyeolhae I need you girl wae dachil geol almyeonseo jakku niga piryohae I need you girl neon areum dawo I need you girl neomu chagawo I need you girl (I need you girl) I need you girl I need you girl"
}