{
  "id": "song_02021",
  "title": "Chúc Tết",
  "artist": "Khởi My",
  "genre": "Điệu Ballad",
  "lyrics": "1. Mùa xuân sang ta chúc nhau Bao ước muốn bao hy vọng Cùng rủ nhau mau bay về Thắm trên môi cười xinh tươi Ta chúc nhau những lời chúc lành Mong tết này tiếng cười khắp trời. 2. Mùa xuân sang ta chúc nhau Năm mới đến mong bao người Hạnh phúc ơi xin bay về Xoá tan bao buồn lo âu Ta nhắp cạn chén rượu ấm lòng Chúc nhau những lời ước hẹn thấm nồng. 3. Mùa xuân sang ta chúc nhau Cho ước muốn bay cao vời Cùng nỗi vui luôn bên người Xoá ưu tư dài đêm đông Ta hãy cùng chúc mừng xuân về Mong tết này mỗi nhà phát tài. 1. Měi tiáo dà jiē xiǎo xiàng Měi gè rén de zuǐ lǐ Jiàn miàn dì yī jù huà Jiù shì gōng xǐ gōng xǐ Gong xǐ gōng xǐ gōng xǐ nǐ yā Gōng xǐ gōng xǐ gōng xǐ nǐ 2. Dōng tiān yǐ dào jìn tóu Zhēn shì hǎo de xiāo xī Wēnnuǎn de chūn fēng Jiù yào chuī xǐng dà dì Gong xǐ gōng xǐ gōng xǐ nǐ yā Gōng xǐ gōng xǐ gōng xǐ nǐ 3. Hào hào bīng xuě róng jiě Yǎn kàn ?méi huā tǔ ruǐ Màn màn cháng yè guò qù Tīng dào yī shēng jī tí Gong xǐ gōng xǐ gōng xǐ nǐ yā Gōng xǐ gōng xǐ gōng xǐ nǐ 4. Jīng guò duō shǎo kùn nán Tì jīng duō shǎo mó liàn Duō shǎo xīn ér pàn wàng Pàn wàng xīn de xiāo xī Gong xǐ gōng xǐ gōng xǐ nǐ yā Gōng xǐ gōng xǐ gōng xǐ nǐ"
}