{
  "id": "song_02082",
  "title": "Harehare ya (Ngày nắng)",
  "artist": "Sou",
  "genre": "Điệu Ballad",
  "lyrics": "Into:   Yo ru no machi mayoishi kegare no ranpo Doko kara kita no yo misuborashii ne Nee uchi ni oide Atatamete ageru yo Ima made yoku ganbatta yo ne Kokora de yasunde mimasen ka Yukkuri hanashi o shimasen ka To riaezu konya wa á a anshinsa Koe wa hidoku itanda Kawaita kawaita Tooku no kitsune ga konkon to Bokutachi o sagashite iru you da Sotto iki o hisometa Kono mama  x2 Itetsuku yuki no naka de Tashikana netsu o obita Ko kyuu o shite Ko e o yaite Moeta moeta Misogi no hi Saa en no kakine o koete Anata o motto shi ritai I enai mama I enai mama Itsu no ma ni ka yuki wa Ame ni nari mashita Yo ake mae anata wa sousou to Anna ni naite ita noni Koboreta koboreta Ima made arigatou san nante Iwainaide yo oitekanaide Kitto kaereyashinai Kono mama Itsuka yume de a ete mo Anata nya kitto todoka nai Bo ku wa koko de Bo ku wa koko de Sode o nurashinagara kaeri o matsu dake Sa a utage no takenawa koete Ikite miyou ka i masara Mi sogi no hi wa Mi sogi no hi wa A me ni ame ni nure te ita Hareta hareta asabora ke Mite ru kana   "
}