{
  "id": "song_02700",
  "title": "Good Bye",
  "artist": "Air Supply",
  "genre": "Điệu Ballad",
  "lyrics": "I can see the pain living in your eyes And I know how hard you try You deserve to have so much more I can feel your heart and I sympa thize And I'll never criti cize all you've ever meant to my life I don't want to let you down I don't want to lead you on I don't want to hold you back From where you might be long You would never ask me why My heart is so guised I just can't live a lie anymore I would rather hurt my self Than to ever make you cry There's nothing left to say but good bye"
}