{
  "id": "song_02812",
  "title": "C.T.A.Đ.M.R",
  "artist": "Đạt G",
  "genre": "Điệu Ballad",
  "lyrics": "Vòng - - - Intro: 2x - - - Sau bao nhiêu đổ vỡ anh lại trở về bên căn phòng Sau bao nhiêu vỡ nát, anh lại đành buông tay của em Đưa nhau đi qua bao nhiêu bão tố buốt giá gần kề Em ơi ! Em quên đường về hay tay em giờ người ta đang nắm Nơi em mang niềm vui, em đi rồi giờ toàn buồn không thôi Khi em mang ánh sáng, cô đơn về gần kề bên anh Con tim anh em lấy mất, nhớ mang về vẹn nguyên em nha ! Con tim anh em cướp mất, lỡ thương rồi làm sao anh quên...íiiii Í i í i...con tim anh em lấy rồi ! Í i í i...con tim anh đâu mất rồi ! Í i í i...con tim anh em lấy rồi ! Í i ì i í i i ì í i i ì Rap: - - - - - - Nơi em mang niềm vui, em đi rồi giờ toàn buồn không thôi Khi em mang ánh sáng, cô đơn về gần kề bên anh Con tim anh em lấy mất, nhớ mang về vẹn nguyên em nha ! Con tim anh em cướp mất, lỡ thương rồi làm sao anh quên...íiiii Í i í i...con tim anh em lấy rồi ! Í i í i...con tim anh đâu mất rồi ! Í i í i...con tim anh em lấy rồi ! Í i ì i í i i ì í i i ì - - -"
}