{
  "id": "song_03152",
  "title": "One Time",
  "artist": "Justin Bieber",
  "genre": "Điệu Ballad",
  "lyrics": " M e plus you, I'm a tell you one time ( repeat 3x ) W hen I met you girl my heart went knock knock No w them butterflies in my stomach wont stop stop An d even though its a struggle love is all we got A n we gon' keep keep climbin' till the mountain top Y our world is my w orld And my fight is you r fight My breath is your breath A nd girl you're my one love M y one life for sure Let me tell you o ne time I'ma tell you one t ime Y ou look so deep you know that it humbles me, Y ou're by my side and troubles them don't trouble me Ma ny have called but the chosen is you Wh atever you want shawty I'll give it to you Yo ur world, your world A nd my fight is you r fight My breath is your br eath And your hurt, I' m not ri ght L et me tell you one time I' mma tell you one time An d I'ma be your one guy, number one girl I'l l be there for you On e time, one t ime y eah it's you I'mma tell you o ne time I'm ma tell you one time I' mma tell you one time"
}