{
  "id": "song_03288",
  "title": "Yêu Yêu Yêu",
  "artist": "Hoàng Tôn",
  "genre": "Điệu Ballad",
  "lyrics": " Ngày hôm qua đẹp xinh quá Kỷ niệm ngỡ như đang ùa về Lòng bối rối con tim thẹn thùng Ta đã trao nhau một tình yêu đầu Rồi ngày hôm nay…đẹp xinh hơn Trở về nơi đôi ta hẹn hò… Lòng vẫn mang bao chứa chan tin yêu Và bờ môi như khẽ chờ ai Con tim nguyện thề luôn yêu yêu sẽ mãi yêu Trao nhau nụ hôn say đắm…vấn vương thật nhiều Không bao giờ sợ những lúc buồn đau vì ta có nhau Từ nay cho đến mai sau đêm đêm chẳng thể vây kín bao giấc mơ này bên em lòng anh chỉ thấy hạnh phúc vơi đầy Như con thuyền đi đến bến bờ xa Ngập tràn tiếng ca Cùng với gió và mây Sẽ trở về nơi này"
}