{
  "id": "song_03614",
  "title": "Chỉ Còn Riêng Anh [Em]",
  "artist": "Đinh Mạnh Ninh",
  "genre": "Điệu Ballad",
  "lyrics": "Chợt tỉnh giấc cơn mơ vừa qua Chiều lặng lẽ mang em thật xa Đường về có cô đơn chờ ai Hay yêu thương em mang về theo giờ đây chỉ là tiếng bóng đêm thở dài Chuyện buồn ấy nguôi ngoai làm sao Nước mắt không rơi làm sao Có lẽ tim em giờ cũng đang bơ vơ tìm giấc mơ yêu thương ngày ấy Đường anh đi còn quá dài Đợi chờ anh còn lắm mệt nhoài Đợi lạnh lẽo em ôm vào giấc em mon g chờ ai Đôi khi anh vội quên mau Cho em muôn ngàn nỗi đau Đâu hay ta lạc mất nhau, có những xa xôi đâu nào biêt Nỗi hoang mang còn giữ riêng Biết đâu tình yêu biết đâu là dối gian Bỡ ngỡ. anh ôm con tim muốn vỡ thẩn thờ…ớ ờ… Lạnh lùng đêm tối vẫn đây"
}