{
  "id": "song_04066",
  "title": "Mừng Em Sinh Nhật",
  "artist": "Lam Trường",
  "genre": "Điệu Ballad",
  "lyrics": " Nắng tô hồng đôi môi, Bao cánh hoa reo vui chúc mừng. Tuổi hồng em có giấc mơ êm đềm Nhìn nàng hàng mi vút cong Nụ cười xinh như đóa hồng Sướng vui nhất hôm nay là anh Bởi vì em luôn trong tim anh dấu yêu nhiều Được bên em, anh luôn mong sao tháng năm dài. Cúi xin ngàn lần ta luôn có nhau Cùng nhau ta chia bao buồn vui Hỡi người tình mình cùng nâng ly Mừng em yêu một tuổi thần tiên Cuộc đời sẽ có mãi những phúc trong tim ta. Anh và em cùng nhau mãi mãi Sẽ không bao giờ, mình rời xa cách. Chúc em sinh nhật, nhiều niềm vui Happy birth day!"
}