{
  "id": "song_04411",
  "title": "Điều Ước Valentine",
  "artist": "Vương Anh Tú",
  "genre": "Điệu Ballad",
  "lyrics": "Vòng hợp âm:  Valentine năm nay thật buồn Valentine cứ đến làm cho lòng tôi u buồn Tìm góc khuất ở nơi chẳng có ai ngồi Chỉ riêng tôi mỗi góc trời rồi suy tư thế thôi Valentine riêng tôi ngậm ngùi Valentine ai cũng cần có một người để vui Tại sao chỉ mỗi tôi giữa biết bao người Nghẹn môi nở một nụ cười là duyên chưa đến thôi Nhiều năm đã chẳng ai rồi Nhiều khi muốn hỏi ông trời đến khi nào tôi hết lẻ loi Đừng chán chê một mình rồi đừng thế nữa đi Đừng khép mi lại ước chi là nửa kia đang ngồi sát bên tôi Tự nhiên muốn thấy em cười Lòng tôi ôi xuyến xao Biết đâu ở ngoài kia em cũng như tôi Cầu xin ông trời chỉ một điều ước thôi thật nhỏ nhoi Một người như tôi... và cho tôi cơ hội Đôi chân tung bay bông hoa lung lay theo mây trời ngất ngây Valentine là ngày gì chẳng biết"
}