{
  "id": "song_04916",
  "title": "Mùa Hoa Trở Lại",
  "artist": "Khánh Linh",
  "genre": "Điệu Ballad",
  "lyrics": "Ngày đó nơi quê tôi Tết về Còn nhớ cái se lạnh cuối năm Ngày đó anh em tôi quây quần Ngồi bên mâm cỗ trông giao thừa Ngày đó Cha tôi mang Tết về Là cành đào thắm khoe sắc mình trước sân Mẹ gói bánh chưng bên hiên nhà Kìa mùa hoa nữa đang trở về Ngày đó chim tung bay khắp trời Dòng thời gian đã qua bao nhiêu mùa hoa và lá Nắng xuân sang rạng rỡ, gió mơn man cánh đào như dáng ai Mùa cũ đã đi qua tháng ngày Giờ mùa hoa nữa đang quay về bình yên lạ thế Sớm mai khi tỉnh giấc, ước sao cho bé lại như ấu thơ...ngày đó Nhìn cánh hoa mai nơi góc tường Chợt nhớ cánh hoa đào lúc xưa Nồi lá ai đun bên hiên nhà Mùi hương đêm khiến đôi mi nhòe Dừng bước đôi chân nơi hiên nhà Mẹ ơi con đã quay....... trở về\""
}