{
  "id": "song_04995",
  "title": "Cám Ơn Em Về Những Ngày Hôm Qua",
  "artist": "Duy Mạnh",
  "genre": "Điệu Ballad",
  "lyrics": "tìm đến nhau lần cuối để q uên đi ngày mai rằng chúng t a ko còn bên n hau thời g ian hay kéo dài để m ột đêm cuối cùng ta d uoc trọn vẹn trao đến n hau. Hãy nói những lời cuối để cho nhau duoc vui rồi mai em đi về bên ấy và e m có biết rằng dù 2 t a cách xa thì a nh cũng vẫn yêu em Biển khơi s óng trào d âng giờ em đi mất rồi anh sẽ k hóc vì nhớ em nhiều l ắm em có biết, em đã đ ến tặng anh niềm vui t rong tiếng c ười, cảm ơn em hằng đ êm những ngày q ua"
}