{
  "id": "song_05092",
  "title": "Tình Yêu Khép Lại",
  "artist": "Cao Tùng Anh",
  "genre": "Điệu Ballad",
  "lyrics": "Một chiều mưa đi bên cạnh em,nắm tay em yêu anh hỏi em Trái tim em yêu anh nhiều không? nhiều như thế nào Em nhìn lên bầu trời và nói,tình yêu em trao anh lớn lao Tình yêu em trao anh nhiều hơn cả những vì sao Ngày hôm nay nơi đây lại mưa,anh vẫn đi trên con đường xưa Nước mắt rơi trong tim,vì không còn em nữa rồi Em bây giờ đã vội thay đổi,em muốn duyên chúng ta chia đôi Lý do chúng ta xa nhau không hợp nhau anh phải Làm sao Giọt mưa rơi vào trong lòng anh buốt giá Câu hứa hôm qua bây giờ đã hóa đá Nước mắt nhạt nhòa trên môi,vì lời nói dối xa vời Đành ôm đắng cay,em cứ đi đi anh không trách em đâu Từ biệt nhau đi từ đây đường ai nấy bước Hãy sống vui lên tương lai chờ em phía trước Chẳng dám yêu thêm một ai,vì là đớn đau quá nhiều Từ nay đến mai sau anh chẳng dám tin ai Và tình yêu trong anh khép lại Tình yêu trong anh .....khép lại"
}