{
  "id": "song_05938",
  "title": "Kiếp Sau Nguyện Làm Một Đóa Sen (来生愿做一朵莲)",
  "artist": "Ngụy Tân Vũ ( 魏新雨)",
  "genre": "Điệu Ballad",
  "lyrics": "Láishēng yuàn zuò yī duǒ lián jìng jìng shèngkāi zài fú qián chū yūní bù rǎn yǐ qīngfēng ér mián huā kāi bù yǔ huā luò wú yán? Láishēng yuàn zuò yī duǒ lián yǔ nǐ zài xù sān shēng yuán bù zǎo yě bù wǎn lái dào nǐ shēn biān bù zài cuòguò bù zài cā jiān? Láishēng yuàn zuò yī duǒ lián huò zài fú qián huò zài nǐ xīn tián yīshēng fēng qīng yún dàn bù jiū yě bù chán yíng fēng shūzhǎn qiǎn xiào yān rán láishēng yuàn zuò yī duǒ lián kǔ là suān tián xǐlè bēi huān děngdào huítóushì' àn xīn bù zài líng luàn suí yù'ér'ān níngjìng zhì yuǎn"
}