{
  "id": "song_06979",
  "title": "Rise Up",
  "artist": "Andra Day",
  "genre": "Điệu Ballad",
  "lyrics": " You’re broken down and tired Of living life on a merry-go-round And you can’t find the fighter But I see it in you so we gonna walk it out And moooooooooove mountains We gonna walk it out And moooooooooove mountains And I’ll rise up I’ll rise up I'll rise up And I’ll do it a thousand times again And I’ll rise up I’ll rise up I'll rise up And I’ll do it a thousands times again For you For You For You For You When the silence isn’t quiet And it feels like it’s getting hard to breathe And I know you feel like dying But I promise we’ll take the world to its feet And mooooooooooove mountains Take the world to its feet And moooooooooove mountains And I’ll rise up I’ll rise up I'll rise up And I’ll do it a thousand times again For you For you For You For You All we need, all we need is hope And for that we have each other And for that we have each other We will rise We will rise We’ll rise, ohh ohhh We’ll rise I’ll rise up I’ll rise up I will rise a thousands times again And we’ll rise up We’ll rise up We’ll rise up And we'll do it a thousands times again For You For You For You For You Ooh, Ooh, Ahh, Ahh"
}