{
  "id": "song_07075",
  "title": "Đừng Để Tôi Biết Em Giối Gian",
  "artist": "Lâm Hùng",
  "genre": "Điệu Slow",
  "lyrics": "Một khi em đã dối gian tôi người yêu hỡi Đừng cho tôi, trông thấy em Vì tôi sẽ chua xót thêm khi miệng tôi phải nói Lời chia tay nghe sao đắng cay Một khi em đã dối gian tôi người yêu hỡi Đừng cho tôi, trông thấy em Vì tôi sẽ chua xót thêm khi miệng tôi phải nói Lời chia tay nghe sao đắng cay Dẫu đây con tim còn yêu em rất nhiều Nhưng giận hờn làm xoá đi tình tôi Có lúc muốn ôm em bỏ qua những lỗi lầm Nhưng vì tự ái tôi không làm được Xin cho tôi quên đi người tôi yêu tình ơi Hay cho tôi quên đi hết lỗi lầm của em Nhưng làm sao quên khi lòng tôi đang yêu em Mà tôi chẳng cần tình yêu gian dối Vì sao em nỡ dối gian người ơi Khi con tim tôi đang còn yêu Tại sao không giữ mối tình ta Đã qua bao tháng năm thần tiên Tại em đam mê, tình yêu mới Vì bao men say, khiến em quên lối Nên em, nên em đã đánh mất mối tình tôi"
}