{
  "id": "song_07318",
  "title": "Tiếng Sáo Phiêu Bồng",
  "artist": "Lam Trường",
  "genre": "Điệu Ballad",
  "lyrics": "1. Dạo bước đi khắp chân trời Có gió có mây theo cùng ta Hành khúc chiếc sáo bên mình những lúc giá rét đêm lạnh lùng 2. Nhạc khúc gieo dắt tâm hồn Tiếng sáo với ta đi ngàn xa Trần thế đêm trắng phũ phàng Ta mong quên hết bao sầu đau ĐK: Nơi chân trời hoàng hôn mình ta đứng trông đàn chim cuối trời Chim bay về đầu non chiều buông khói lam bên mái tranh nghèo Nghe dạt dào triền miên ngoài kia như tiếng sáo hòa cùng mây trời thiên nhiên Tiếng sáo chói lên thay vầng thơ Ta mong được làm mây dạo bay khắp nơi lạc chốn phiêu bồng Ta không màng lợi danh trần gian thế nhân đầy những lọc lừa. Nơi sông hồ nghèo thương đời ta như cánh én hòa cùng mây trời gió mát. Chẳng nghĩ đến chi bao phiền lo"
}