{
  "id": "song_07413",
  "title": "Hoa Đăng",
  "artist": "Truant Fu",
  "genre": "Điệu Ballad",
  "lyrics": "    Nói em về giấc mơ của anh Lấy xe mình phóng thật nhanh Dạo vòng từng con phố Tới khi đèn đường chiếu qua mặt hồ Nói anh vì sao em lại không Muốn hai ta sẽ thành đôi Chờ đợi gì hơn nữa? Với anh, chỉ cần có em bên cạnh Có khi anh chẳng hay biết Với đống dối gian em mang hàng tấn trên vai Đến nỗi em khóc oà uh babe Có khi anh thật vô lí Lấy hết lí do em nên cầm lấy tay anh Khi em chưa sẵn sàng Cause I love you so bad Just want to hold you forever Cause I love you so baddd Nói yêu em ngàn lần Biết đâu liệu ta có còn nhau Sẽ như vậy mãi về sau Nụ cười tan trong gió Cuối đông từng đợt tái tê trong lòng Nói anh vì sao em lại không Muốn hai ta sẽ thành đôi Chờ đợi gì hơn nữa? Với anh, chỉ cần có em bên cạnh Có khi anh chẳng hay biết Với đống dối gian em mang hàng tấn trên vai Đến nỗi em khóc oà uh babe Có khi anh thật vô lí Lấy hết lí do em nên cầm lấy tay anh Khi em chưa sẵn sàng Cause I love you so bad Just want to hold you forever Cause I love you so baddd Nói yêu em vậy thôi. "
}