{
  "id": "song_07701",
  "title": "Anh Vi Cá (Vi Cá Tiền Truyện OST)",
  "artist": "Thái Vũ (BlackBi)",
  "genre": "Điệu Ballad",
  "lyrics": "Mày thích chơi tới đâu thì tao chiều mày tới đó Mày thích chơi tới đâu thì tao chiều mày tới đó Đời đẻ tạo ra thằng Vi Cá này Bước ra đường anh em tao là cha là chú Mày thích chơi tới đâu thì tao chiều mày tới đó Mày thích chơi tới đâu thì tao chiều mày tới đó Đời mày đã chấp nhận chơi (chơi) Bước ra đường, anh em tao là cha là chú Mày thích chơi tới đâu thì tao chiều mày tới đó"
}