{
  "id": "song_08154",
  "title": "Đến Cuối Cùng Lại Cô Đơn",
  "artist": "Anh Tú Atus",
  "genre": "Điệu Ballad",
  "lyrics": "Thôi đừng về hãy ở lại đây được không, được không? Chuyện hôm qua mình xé đi trong tim anh vẫn còn thương em rất nhiều Thôi đừng về nữa mai này đường đời còn ai ngóng chờ Một người muốn đi. Một người ở đây trong lòng buồn dâng Vì rằng nhiều lúc để nỗi nhớ em ngập tràn vào tâm tư Anh muốn hét lên nhưng không thể được Dòng người lướt nhanh đoạn đường vắng tanh Chỉ một người thả tâm hồn vào Bóng đêm tối tăm vỡ tan dẫu lệ nay đã khô, tâm tư còn đầy Cơn mưa rơi rơi vội qua ai ôm từ sau, trong cơn mê Dẫu đã cách xa mãi trong nắng mà như giá băng con tim khờ dại Em như sương mai mỏng manh bên nhau bao năm đến cuối cùng lại cô đơn Em ở lại đây đừng về Anh ôm bao âu lo toan bộn bề Vài người đến nhưng rồi cũng đi thôi Sao em vẫn đến dù biết chắc sẽ chia đôi Nhưng a biết kết quả sẽ giống như lần trước Vậy thôi đừng về em ở lại đây được không? Tim em là nắng nên anh sẽ thắng được đông Just pick up the phone, turn on the tone,"
}