{
  "id": "song_08983",
  "title": "Only One For Me",
  "artist": "BTOB",
  "genre": "Điệu Ballad",
  "lyrics": "Tone nan jigeum nege ga go itneun giriya bome kkeut boda hwol sshin ppareu ge hal mari itneun geol malhaji aneumyeon pyeongsaengeul huhweham yeo sal geot gata amado sal geot ga ta neorang sum shwi myeon jeongshin mot charige sseo nuni gamgi go I just want you to know I’m the real one that you’re looking for geo kjeongeun buranham ane gadwo geonneopyeone da nwadugo ijebuteo uri sa jin juwo dama ne sonagwi ane agija gi georeo dul geoya eodideunji boige hae jwo na eop shin an dwenda haejwo neo eopshin an dwenda nan neoyeo ya handa amuri saenggakhaedo nan gyeolguk neoya huhweha gin shilta neoreul sarang handa Cause you are the only one naneun neoppuniraneun geol Hah ah ah ah ah ah ah Let’s get it on let’s get it on Hah ah ah ah ah ah ah Why don’t you be my girl Hah ah ah ah ah ah ah Let’s get it on let’s get it on Cause you are the only one for me ajikdo nege gago itneun giriya yeoreumbam gonggibo da tteugeob ge geuriwo haetteon neol butjabji mothamyeon pyeongsaengeul huhweham yeo sal geot gata nega neomu bogo shipeoseo yeah yeah yeah Girl I swear this ain’t no booty call na na na geunyang saenggaknaseo haneun geotto aniya (nope) deudieo jeongshin charyeosseo neo eopshin an dwendaneun geol Now I know now I know dashi shijakhae bol saenggak isseu myeon cheoeumcheoreom mannal saenggagi isseumyeon lemme know Let’s give it a go neo eopshin an dwenda nan neoyeo ya handa amuri saenggakhaedo nan gyeolguk neoya huhweha gin shilta neoreul sarang handa Cause you are the only one for me na ye yeoreum neol eotteoke hagetni hae reul myeot beoneul neomgyeodo you and me neoreul saranghae saranghae tto malhago malhaedo o jik neoyeoyaman I can live uri tteugeob ge jabeun son kkwak jaba deo yeoreumbame love kkwak ana deo dugeundugeun urin gureum gureum wi idaero uri dul i neo eopshin an dwenda nan neoyeo ya handa amuri saenggakhaedo nan gyeolguk neoya huhweha gin shilta ...neoreul sa ranghanda Cause you are the only one naneun neoppuniraneun geol Hah ah ah ah ah ah ah Let’s get it on let’s get it on Hah ah ah ah ah ah ah Why don’t you be my girl Hah ah ah ah ah ah ah Let’s get it on let’s get it on Cause you are the only one for me"
}