{
  "id": "song_09298",
  "title": "Little Apple (小苹果)",
  "artist": "Chopstick Brothers",
  "genre": "Điệu Ballad",
  "lyrics": "Wǒ zhǒng xià yī kē zhǒngzǐ zhōngyú zhǎng chūle guǒshí jīntiān shìgè wěidà rì zi zhāi xià xīngxīng sòng gěi nǐ zhuāi xià yuèliàng sòng gěi nǐ ràng tàiyáng měitiān wèi nǐ shēng qǐ biàn chéng làzhú ránshāo zìjǐ zhǐ wéi zhào liàng nǐ bǎ wǒ yīqiè dōu xiàn gěi nǐ zhǐyào nǐ huānxǐ nǐ ràng wǒ měi gè míngtiān dū biàn dé yǒu yìyì shēngmìng suī duǎn ài nǐ yǒngyuǎn, bù! Lí! Bù! Qì! Nǐ shì wǒ de xiǎo ya xiǎo píngguǒ zěnme ài nǐ dōu bù xián duō hóng hóng de xiǎo liǎn er wēnnuǎn wǒ de xīn wō diǎn liàng wǒ shēngmìng de huǒ huǒ huǒ huǒ huǒ huǒ nǐ shì wǒ de xiǎo ya xiǎo píngguǒ jiù xiàng tiānbiān zuì měi de yúnduǒ chūntiān yòu lái dào le huā kāi mǎn shān pō zhǒng xià xī wàng jiù huì shōuhuò cóng bù juédé nǐ tǎoyàn nǐ de yīqiè dōu xǐhuān yǒu nǐ de měitiān dū xīn xiān yǒu nǐ yángguāng gèng cànlàn yǒu nǐ hēiyè bù hēi’àn nǐ shì báiyún wǒ shì lán tiān chūntiān hé nǐ mànbù zài shèng kāi de huācóng jiān xiàtiān yèwǎn péi nǐ yīqǐ kàn xīngxīng zhǎyǎn qiūtiān huánghūn yǔ nǐ chángyáng zài jīnsè màitián dōngtiān xuěhuā fēiwǔ yǒu nǐ, gèng! Jiā! Wēn! Nuǎn! Nǐ shì wǒ de xiǎo ya xiǎo píngguǒ zěnme ài nǐ dōu bù xián duō hóng hóng de xiǎo liǎn er wēnnuǎn wǒ de xīn wō diǎn liàng wǒ shēngmìng de huǒ huǒ huǒ huǒ huǒ huǒ nǐ shì wǒ de xiǎo ya xiǎo píngguǒ jiù xiàng tiānbiān zuì měi de yúnduǒ chūntiān yòu lái dào le huā kāi mǎn shān pō zhǒng xià xī wàng jiù huì shōuhuò Nǐ shì wǒ de xiǎo ya xiǎo píngguǒ zěnme ài nǐ dōu bù xián duō hóng hóng de xiǎo liǎn er wēnnuǎn wǒ de xīn wō diǎn liàng wǒ shēngmìng de huǒ huǒ huǒ huǒ huǒ huǒ nǐ shì wǒ de xiǎo ya xiǎo píngguǒ jiù xiàng tiānbiān zuì měi de yúnduǒ chūntiān yòu lái dào le huā kāi mǎn shān pō zhǒng xià xī wàng jiù huì shōuhuò"
}