{
  "id": "song_09413",
  "title": "Je m'appelle Hélène",
  "artist": "Hélène Rollès",
  "genre": "Điệu Ballad",
  "lyrics": "Hélène. Je m'appelle Hélène Je suis u ne fille. Comme les au tres Hélène. J'ai mes joies mes peines Elles font ma vie. Comme la vôtre Je vou drais trou ver l'a mour Simple ment trou ver l'a mour Hélène. Je m'appelle Hélène Je suis u ne fille. Comme les au tres Hélène Si mes nuits sont pleines De rêves de poèmes/ Je n'ai rien d'au tre Je vou drais trou ver l'a mour Simple ment trou ver l'a mour Et même. Si j'ai ma photo Dans tous les journaux. Chaque se maine Personne. Ne m'attend le soir Quand je ren tre tard Personne ne fait battre mon cur Lorsque s'é teignent les projecteurs Hélène. Je m'appelle Hélène Je suis u ne fille. Comme les au tres Je vou drais trou ver l'a mour Simple ment trou ver l'a mour Et même. Quant à la télé Vous me re gardez. Sourire et chante Personne. Ne m'attend le soir Quand je ren tre tard Personne ne fait battre mon cur Lorsque s'é teignent les projecteurs Hélène. Je m'appelle Hélène Je suis u ne fille. Comme les au tres Hélène. Et toutes mes peines Trouverons l'oubli. Un jour ou l'au tre Je vou drais trou ver l'a mour Simple ment trou ver l'a mour"
}