{
  "id": "song_09434",
  "title": "Chợ Tình",
  "artist": "Pb Nation",
  "genre": "Điệu Ballad",
  "lyrics": "Đôi mắt em long lanh Như giọt sương trong nắng Làn gió mát theo em bay lên, về từ núi cao Đôi mắt em long lanh Con tim anh cồn cào Tình yêu đến anh say lòng ngất ngây anh thầm mong Ai a i a ôh ốh Ai a i a ôh ôh Nói sao hết được tấm chân tình này Hát lên ngàn câu thiết tha Nếu em là gió trời Anh là mây để gió lả lơi Những rung động tuyệt vời mà ta trao nhau (yeah) Để mãi sau này không rời Gió và mây sẽ cứ rong chơi Tựa vào vai anh... ớ ơ ơ Ing Lả Ơi ... Vẫn những bước chân em đang tìm về anh Phải làm sao để thấy em rạng rỡ hoa mùa xuân Mình cùng khiêu vũ dưới ánh trắng khuya Nghe nhịp tim rộn rã, Đừng rời xa anh, Mình cùng đợi nắng quay lại trên đồi Ai a i a ôh ốh Ai a i a ôh ôh Nói sao hết được tấm chân tình này Hát lên ngàn câu thiết tha Nếu em là gió trời Anh là mây để gió lả lơi Những rung động tuyệt vời mà ta trao nhau (yeah) Để mãi sau này không rời Gió và mây sẽ cứ rong chơi Tựa vào vai anh... ớ ơ ơ Ing Lả Ơi ... Nếu em là gió trời Anh là mây để gió lả lơi Những rung động tuyệt vời mà ta trao nhau (yeah) Để mãi sau này không rời Gió và mây sẽ cứ rong chơi Tựa vào vai anh... ớ ơ ơ Ing Lả Ơi ..."
}