{
  "id": "song_10199",
  "title": "Này Cô Em Xinh",
  "artist": "Nguyễn Đức Cường",
  "genre": "Điệu Disco",
  "lyrics": "Một chiều trên phố, gặp cô em xinh tươi Đằng sau đôi chân thon, dăm ba chú chó đang lon ton Người qua lại đang ngắm nhìn, tim đập them mấy nhịp Người đâu mà xinh thật xinh, ai cũng quan tâm Đứng lại gàn anh em ơi, anh đùa giỡn chút thôi à Anh muốn dặn cho cô em Đi qua ngày nắng với mưa giông, từng chiều vắng, đôi chan em về lối ấy Anh mong tìm lại phút giây này, một lần nữa 2 ta sẽ cùng chung bước Lần đầu tin nhìn em anh chợt như người say nắng Vờ hỏi han vài câu mong làm quen khi cách xa Anh muốn gặp lại nụ cười hôm nao Em hỡi chừng nào lại về qua đây"
}