{
  "id": "song_10399",
  "title": "Lúm đồng tiền nhỏ (小酒窝)",
  "artist": "Ah Sa",
  "genre": "Điệu Blues",
  "lyrics": "Wǒ hái zài xúnzhǎo yīgè yīkào hé yīgè yǒng bào Shuí tì wǒ qídǎo tì wǒ fánnǎo wèi wǒ shēngqì wèi wǒ nào Xìngfú kāishǐ yǒu yùzhào yuán fèn ràng wǒmen màn man jǐn kào Ránhòu gūdān bèi tūnmò liǎo wúliáo biàn de yǒu huà liáo yǒu biànhuà le Xiǎo jiǔwō zhǎng jiémáo shì nǐ zuìměi de jìhào Wǒ měi tiān shuì bùzháo xiǎngniàn nǐ de wéixiào Nǐ bù zhīdào nǐ duì wǒ duōme zhòngyào Yǒu le nǐ shēngmìng wánzhěng de gānghǎo Xiǎo jiǔwō zhǎng jiémáo mírén de wú kě jiù yào Wǒ fàng màn le bùdiào gǎnjué xiàng shì hē zuì le Zhōngyú zhǎodào xīnyǒulíngxī dì měihǎo Yībèizi nuǎn nuǎn de hǎo Wǒ yǒngyuǎn ài nǐ dào lǎo"
}