{
  "id": "song_10611",
  "title": "HÀNH KHÚC SINH VIÊN KHOA ĐIỆN",
  "artist": "Various Artists",
  "genre": "Điệu Disco",
  "lyrics": "Ở đâu có bước chân những kĩ sư khoa điện Ở đâu có bước chân những con người trẻ trung Nhũng cô gái chàng trai đang ngày đêm chung sức Đem dòng điện bao la thắp sáng cuộc đời này Tình yêu với chúng tôi là những nụ cười Tình yêu với chúng tôi là dòng điện sáng tươi Tình yêu với chúng tôi là tiếng ca yêu đời Là khúc hát quê hương đang ngày đêm mong chờ Hãy hát lên hát lên bài ca Bài ca chúng tôi những sinh viên khoa điện Năm mươi năm anh hùng truyền thống Đang vươn cao vào tương lai Hãy hát lên hát lên bạn ơi Hành khúc chúng tôi những sinh viên khoa điện Cho hôm nay một niềm tin mới Và ngày mai đất nước mình hóa thân Hành trang chúng tôi đi vào tương lai Là những đôi chân không ngại gian khó Là những đôi tay không khi nào biết nghỉ Biến dòng nước kia thành điện sáng cho đời"
}