{
  "id": "song_10635",
  "title": "Theo Anh Không?",
  "artist": "JustaTee",
  "genre": "Điệu Ballad",
  "lyrics": "Anh đây là nước sinh ra đã luôn nhẹ nhàng Chưa ai thèm rước trong khi đẹp trai đứng đầu làng Em đây thì khác chanh \"chua\" thì không gì bằng Nhưng thơm dịu mát bao thanh niên rụng tim, pằng pằng Vậy thì em có muốn theo anh không? Có muốn theo anh không? Lấy chất thơm trong em ta hòa cùng với chất riêng trong anh *yeah yeah* Biến ra Ô Long Chanh, biến ra Ô Long Chanh Lấy anh không lo nặng nề, mình cùng vút bay lên mây xanh Đã Ngon, còn Nhẹ. Nhẹ, đã Ngon, còn Nhẹ, Nhẹ Đã Ngon, còn Nhẹ. Nhẹ, Biến ra Ô Long Chanh, Chanh Đã Ngon, còn Nhẹ. Nhẹ, đã Ngon, còn Nhẹ, Nhẹ Đã Ngon, còn Nhẹ. Nhẹ, Biến ra Ô Long Chanh, Chanh Vậy thì em có muốn theo anh không? Có muốn theo anh không? Biến ra Ô Long Chanh, biến ra Ô Long Chanh Không ai cản bước khi ta cùng nhau hòa vào Anh đi đằng trước em theo đằng sau rất ngọt ngào Nhân đôi cảm xúc Ô Long và Chanh diệu kỳ Uống thêm một chút ngon hơn mà không sợ phì Vậy thì em có muốn theo anh không? Có muốn theo anh không? Lấy chất thơm trong em ta hòa cùng với chất riêng trong anh *yeah yeah* Biến ra Ô Long Chanh, biến ra Ô Long Chanh Lấy anh không lo nặng nề, mình cùng vút bay lên mây xanh Đã Ngon, còn Nhẹ. Nhẹ, đã Ngon, còn Nhẹ, Nhẹ Đã Ngon, còn Nhẹ. Nhẹ, Biến ra Ô Long Chanh, Chanh Đã Ngon, còn Nhẹ. Nhẹ, đã Ngon, còn Nhẹ, Nhẹ Đã Ngon, còn Nhẹ. Nhẹ, Biến ra Ô Long Chanh, Chanh"
}