{
  "id": "song_10941",
  "title": "Oh My Heart (#ÔITIMTUI)",
  "artist": "Saa",
  "genre": "Điệu Ballad",
  "lyrics": "Tone Vòng hợp âm:  Lả lướt mỗi đêm vài dòng tin nhắn em viết lên Môi bỗng ngân nga vài lời ca không tên Ring ring ding ding à người đã reply cho em Rồi cả đêm chẳng ngủ được vì anh Người ta bảo là yêu đó, là thuơng đó, là tương tư đợi mong Còn mẹ em bảo là ngốc đó, chẳng trông mong, chẳng dám tin ông nào Nhưng biết làm sao đây khi trái tim này, ca vang xa đến tai người Tung tung tung đập tung tung mỗi khi cạnh anh Oh my heart ! Đừng làm tim em đau nhói thêm khi anh cạnh cô khác Oh my heart ! Sao cứ im lặng, chẳng nói năng sao anh lạnh như băng Oh my heart ! My heart ! Lại thêm 1 lần vỡ tung Khi anh nói rằng: “anh cũng thích em!” Người ta bảo là yêu đó, là thuơng đó, là tương tư đợi mong Còn mẹ em bảo là ngốc đó, chẳng trông mong, chẳng dám tin ông nào Nhưng biết làm sao đây khi trái tim này, ca vang xa đến tai người Tung tung tung đập tung tung mỗi khi cạnh anh Ta da ta da, lời anh nói sao ấm áp lạ thường Ta da ta da, lời em nói lúng túng chẳng ngừng được Ta da ta da, là khi môi người khẽ nói cười Ta da ta da, làm lòng em trót yêu người"
}