{
  "id": "song_11648",
  "title": "Tình Yêu Và Những Ngày Buồn",
  "artist": "Adeline (Ánh Tuyết)",
  "genre": "Điệu Blues",
  "lyrics": "Tone 1. Có những ngày buồn em hát vang la la la la la Gió ghé làm lòng man mác buồn Nhớ đến một thời say đắm, tay mình còn nắm Đi bên nhau Có những ngày buồn em hát vang la la la la la Chất chứa làm lòng tan nát Mà chẳng thấu giờ người nơi đó Bên một ai có vui hơn chăng Thước phim xưa em vẫn xem hằng ngày Còn nhớ hay quên, anh trách em bầy hầy Quần áo lung tung , cứ than tìm mặc không thấy Quán quen xưa, nay mỗi em thường ngồi Vẫn thế thôi anh , em uống không gọi mồi Đàn hát vu vơ, cớ sao mình hoài ngu ngơ 2. Có những ngày buồn em hát vang la la la la la Môi hôn ngày đầu em ngỡ như còn Chợt nhớ đến chiều người quay gót Thương tình chua xót, trôi qua mau Có những ngày buồn em hát vang la la la la la Chất chứa làm lòng tan nát Mà chẳng thấu giờ người nơi đó Bên một ai có vui hơn chăng Thước phim xưa em vẫn xem hằng ngày Còn nhớ hay quên, anh trách em bầy hầy Quần áo lung tung , cứ than tìm mặc không thấy Quán quen xưa, nay mỗi em thường ngồi Vẫn thế thôi anh , em uống không gọi mồi Đàn hát vu vơ, cớ sao mình hoài ngu ngơ"
}