{
  "id": "song_11730",
  "title": "Love Me More",
  "artist": "The Sheep",
  "genre": "Điệu Blues",
  "lyrics": "Tone Lần đầu gặp em anh thấy chúng ta Cứ giống như là quen nhau rất lâu, chẳng thể rời xa nhau Và rồi giờ đây anh mới biết em cũng đã yêu thầm anh từ rất lâu Phải không em? Ước mỗi khi em buồn anh ở đây để vỗ về Ước mỗi khi tan làm anh sẽ luôn nghĩ đến em Ước mỗi khi mưa lạnh anh sẽ ôm chặt lấy em Và nói... Đừng rời xa anh nhé, anh muốn em của anh thôi Vì giờ đây anh đã trót yêu em nhiều lắm Vậy thì tại sao không tỏ tình Anh cứ nói ra thôi rằng anh đang yêu em ... Từ giờ anh sẽ yêu mình em đó giống như là trong mơ Muốn bên em suốt đời anh không muốn buông tay vì Biết đâu ngày mai em sẽ yêu một ai khác Thế nên anh mới nôn nao mong chúng ta một nhà Anh đó anh đó .. Có yêu em nhiều không Anh đó anh đó .. Love me more Anh á anh á .. Có yêu em nhiều không Anh á anh á .. Love me more"
}