{
  "id": "song_12079",
  "title": "dự báo thời tiết hôm nay mưa (demo)",
  "artist": "Grey D",
  "genre": "Điệu Blues",
  "lyrics": "Đoạn dạo nhạc:  - Tiếng mưa rơi bên ngoài ô kính anh nhìn ra Tiếng mưa như đang nhìn thấu tâm tình ta Nhành hoa hướng dương kia nhạt đi Một màu hoa khác không như mọi khi Hoặc chỉ là do tiếng mưa rơi Làm cảm giác ta như vậy thôi Tiếng mưa rơi bên ngoài ô kính trong chiều nay Sắp tan ca rồi nhưng làm sao đón em về đây Vì anh biết em sẽ làm ngơ bỏ mặc anh dưới mưa ôm mộng mơ Rồi cùng người yêu mới lạnh lùng đi về phía xa mờ Mặt trời chằng còn cần thiết Chỉ một người biết làm điều gì để mưa hết rơi... Và bài nhạc buồn này được viết bởi 1 gã si tình huh uh oh Liệu rằng giờ này người mới Đường về lạnh có thay cho em chiếc áo khi mưa ướt đôi vai Rồi nhẹ nhàng đặt một nụ hôn vào làn môi đã từng Là của anh Hết thứ hai ngày lại đến thứ ba Gió cứ bay dòng người vẫn cứ qua Phố sẽ đông vì trời có nắng mai Còn những lúc mưa ngoài đường chẳng có ai Những hạt mưa trên cây vẫn còn lay động Ly rượu vang ở trên tay anh còn cay nồng Mọi thứ vẫn cứ thế đêm ngày xoay vòng Vì sao chỉ có mỗi em là thay lòng ú u ú ù Mây màu đen ngoài ô cửa kính che từng ngôi nhà U ú u ú ù View này anh thường hay ngồi chill em thì pha trà ấm Căn phòng hai người yên bình lắm Chúng ta thường ra ngồi đây và ngắm mưa Nhưng giờ đâu còn nữa đâu Mặt trời chằng còn cần thiết Chỉ một người biết làm điều gì để mưa hết rơi... Và bài nhạc buồn này được viết bởi 1 gã si tình huh uh oh Liệu rằng giờ này người mới Đường về lạnh có thay cho em chiếc áo khi mưa ướt đôi vai Rồi nhẹ nhàng đặt một nụ hôn vào làn môi đã từng Anh đã từng nghĩ suốt cuộc đời này em chỉ trao mình anh mà thôi Dạo: - - - - - - - Liệu rằng giờ này người mới đường về lạnh có thay cho em Chiếc áo khi mưa ướt đôi vai Rồi nhẹ nhàng đặt một nụ hôn vào làn môi đã từng Là của riêng mình anh thôi"
}