{
  "id": "song_12092",
  "title": "Sexy love",
  "artist": "T-ara",
  "genre": "Điệu Blues",
  "lyrics": "geudaero meomchwoyo Sexy love geueu khan nunbicheul gadeuk dameun Sexy love cheorongseong gateun naega heundeullyeo naengcheol haetdeon nae saeng gagi jigeum heundeullyeo i jjaritan bame tteugeoun nun bichi nalbureu neyo (ireoke naemameul humchyeoga) geogi meom chwoyo naegero wayo nae mameul ije badajwo yo neon jeongmal sexy nun sexy ko sexy ip Sexy love nae nunen modeunge da Sexy Oh sexy eyes sexy nose sexy mouth don’t you know oneul nan nega jeongmal Sexy NO NO NO NO can you feel my love nae mameul neukkina yo( oh!) NO NO NO NO can you feel my heart naegerowa To night night night geudaega naege wa seo nae maeumeul humchyeogas seo ije eotteokhae (I can’t stop this feeling) ne ne ne ne maeu me kkok Let let let lets make a bomb Down up down up down"
}