{
  "id": "song_12175",
  "title": "You Are Mine",
  "artist": "Vũ Cát Tường",
  "genre": "Điệu Blues",
  "lyrics": "Tone Trưa nay em đi đâu với ai Đừng quên nhắn một câu với anh Nhiều người sẽ hỏi em sao anh quá khó khăn Thì để anh trả lời thế giới rằng You are mine ah mine ah mine ah mine ah mine Mine ah mine ah mine ah mine ah mine Anh chỉ muốn em yêu có anh thôi mỗi anh thôi She's mine ah mine ah mine ah mine ah mine Mine ah mine ah mine ah mine ah mine Anh chỉ muốn đôi ta mãi chung đôi có nhau thôi Mai anh phải đi xa rất xa Mình em không được la cà quán xá Nhiều người sẽ hỏi em sao anh quá khó khăn Thì để anh trả lời thế giới rằng You are mine ah mine ah mine ah mine ah mine Mine ah mine ah mine ah mine ah mine Anh chỉ muốn em yêu có anh thôi mỗi anh thôi She's mine ah mine ah mine ah mine ah mine Mine ah mine ah mine ah mine ah mine Anh chỉ muốn đôi ta mãi chung đôi có nhau thôi Anh không mong chi đâu xa Chỉ mong sao cho hai ta Yêu nhau thôi, chỉ cần yêu nhau thôi Bên nhau sống vô tư yên vui mang theo đến trọn đời Anh không mong chi đâu xa Chỉ mong sao cho hai ta Yêu nhau thôi, chỉ cần yêu nhau thôi Bên nhau sống vô tư yên vui mang theo đến trọn đời Chỉ cần đôi lời hứa đó Nhưng cần cả đời chứng tỏ Anh và em cũng đôi khi sợ lo vì nếu lỡ một mai nhiều sóng gió Chỉ cần đôi lời hứa đó Nhưng cần cả đời chứng tỏ Anh và em cũng đôi khi sợ lo vì nếu lỡ một mai nhiều sóng gió"
}