{
  "id": "song_12870",
  "title": "Đúng vậy em đẹp nhất trên thế gian này",
  "artist": "Minh Lý",
  "genre": "Điệu Blues",
  "lyrics": " Đúng vậy, em đẹp nhất trên thế gian này Gặp em vào thời điểm anh đang trắng tay Chả lẽ chỉ riêng ta không may mắn vậy Muốn ôm chặt lấy em nhưng tiếc là em không dang tay Yêu em là trọng tội anh sẵn sàng ra pháp trường Bài thánh ca không gọi tên anh trong lễ đường Bao tâm sự không còn là lời rap thường Như hai đường thẳng cắt nhau rồi mãi rẽ hướng Nên đừng tiếc Rừng biếc Những việc Ngừng viết! Thiệt! Ác liệt Gượng ép tự giác viết Kỉ niệm ngày đó hôm nay đành phải chôn sâu Không có em như trái đất này sẽ ngừng quay Rồi ta lẻ bóng dưới con đường này Thường ngày ! Đứng dậy ghế đá ai nắm tay ? Lạc lõng quý giá biết bao nhiêu những năm tháng bình thường ấy Thương thầy.... dạy mày như con và thương mày Sương dày.... phủ bóng đời người mày đương thấy Sao ngày nào tỏ tình vẫn còn gượng vậy ? Mà giờ chả còn phân biệt hướng đông hay hướng tây Sống và chết đi theo một quy luật Ta biết trăn trối gì đến khi mất ? Cuộc đời này phí thật, còn bao nhiêu điều bí mật Tự nhận điều xấu xí nhất "
}