{
  "id": "song_12894",
  "title": "Hóa Thân Thành Cơn Mưa",
  "artist": "Lê Quốc Đạt",
  "genre": "Điệu Blues",
  "lyrics": "Tone Có khi nào em nhớ về những ngày tháng đã qua Có một người đã đến và lau đi giọt nước mắt Ở trên mi người anh thương , như cơn mưa kia nặng hạt Chăm sóc em lau đi giọt nước mắt rơi Có khi nào em tiếc về những điều đã xảy ra chưa Em bước về phía ấy rời xa khỏi vòng tay anh Bỏ quên lời thì thầm của mưa , bước đến nơi ánh nắng vàng Bỏ lại phía sau , ngày mưa em đã từng yêu Hóa thân thành cơn mưa để lau nước mắt rơi mỗi khi em đau Anh hóa thân thành cơn mưa để đến với em khi em buồn Dù sao cũng chỉ là cơn mưa chẳng thể níu em quay lại Gần bên em rồi sẽ vỡ tan trong ánh nắng mai rạng ngời Vì anh không thể bên em , sẽ tan biến khi em hạnh phúc Liệu rằng em còn nhớ đến anh một cơn mưa qua Có khi nào em chợt nhìn thấy mưa Rưng rưng như đang rơi giọt lệ Có bao giờ em khóc khi đấy chưa Ai đón đưa em đi trên lối về Khi em khóc và che đi nước mắt Khi em buồn vì ai quên câu thề Nhưng ánh nắng tới rồi em quên mau Những âu yếm tháng ngày ta bên nhau Em bước đến hào quang và quên mau Cơn mưa ngày nào cùng em qua thương đau Nhưng không trách đâu , Ánh nắng vàng tới mưa tan biến mau Nỗi đau này mưa xin sẽ khắc sâu Cơn mưa hóa thành thương đau nhưng em có biết đâu"
}