{
  "id": "song_13029",
  "title": "tái chế con tim",
  "artist": "Mèow Lạc",
  "genre": "Điệu Blues",
  "lyrics": "intro: I've been hurt I've been let down By the lies, un solicited truths Fill me up throw me out It's a cycle I cannot just break through If only I get one more chance If only I give you one more chance If only I get one more chance If only I give you one more chance Có thể tái chế con tim này và dùng lại được không? Anh nào có muốn đau như vậy, mình dừng lại được không? Có thể tái chế con tim này và dùng lại được không? Anh nào có muốn đau như vậy, mình dừng lại được không? úuu ú u u ù, mình dừng lại được không lại được không lại được không lại được không x2 Give it all , give me something I'm not a knight I swear I'm not that brave Comes and goes , never changing With each re lationship I learn to behave If only I get one more chance If only I give you one more chance If only I get one more chance If only I give you one more chance Có thể tái chế con tim này và dùng lại được không? Anh nào có muốn đau như vậy, mình dừng lại được không? Có thể tái chế con tim này và dùng lại được không? Anh nào có muốn đau như vậy, mình dừng lại được không? So if I can't learn how to love, I think I've had enough outro:      "
}