{
  "id": "song_13425",
  "title": "Đông là khi",
  "artist": "Huy Lê",
  "genre": "Điệu Slow",
  "lyrics": "Nghe đài báo rằng mấy hôm nữa là rét rồi, mà sao vẫn thấy xa xôi Mỗi buổi sáng thức giấc tôi ngước nhìn lên trời, và nhiệt độ vẫn ba mươi Muốn ra phố mùa đông và hít 1 hơi dài, để lạnh run khẽ đôi vai Nhấm 1 ly trà nóng và bát phở tái gầu, thế là quên hết lo âu Và đương nhiên, điều cần lo, mặc k đủ ấm thì sẽ hay ho Còn chuyện người yêu , lý do nào đó năm nay chưa có thì cũng ko lo Đông là khi mà anh với em ra đường, 1 đôi áo khoác, đi dạo phố phường Đông là khi mà ông với tôi la cà, cà phê ấm nóng, ôm đàn hát ca Sáng nay thức dậy đi học thấy trời rét rồi, chỉ thèm nằm quấn chăn thôi May sao có thông báo rằng không phải đến trường, ngày đẹp như hoa hướng dương Nhắn 1 tin hỏi han rằng em dậy lúc nào, rồi chuyện ăn sáng ra sao Ăn 1 bát phở nóng rồi xách đàn đi kèm, và gọi luôn mấy an hem Và đôi khi, chẳng đâu xa, niềm vui ngày rét là chính chúng ta Hẹn hò gặp nhau, đi dạo thật lâu, và nói những câu chuyện không cuối không đầu. Đông là khi mà anh với em ra đường, 1 đôi áo khoác, đi dạo phố phường Đông là khi mà ông với tôi la cà, cà phê ấm nóng, ôm đàn hát ca Đông là khi định thức giấc lúc 5h, tỉnh dậy đã thấy hơn 12h Đông là khi được ôm lấy em trong lòng, hỏi rằng em có thấy lạnh nữa không"
}